clusterers/__init__.py
clusterers/k_means.py
decomposers/__init__.py
decomposers/pca.py
regressors/ElasticNet.py
regressors/L1Regressor.py
regressors/L2Regressor.py
regressors/__init__.py
regressors/baseRegressor.py
regressors/linearCF.py
regressors/linearGD.py
regressors/multipleGD.py
regressors/polylinear.py
small_neural_net/__init__.py
small_neural_net/driverMNL.py
small_neural_net/mnl.py
mlzero-0.1.2.dist-info/METADATA
mlzero-0.1.2.dist-info/WHEEL
mlzero-0.1.2.dist-info/top_level.txt
mlzero-0.1.2.dist-info/RECORD
