Metadata-Version: 2.4
Name: mlzero
Version: 0.1.2
Summary: Machine Learning from Scratch - Educational Python Library
Home-page: https://github.com/bzubs/MLzero
Author: Aditya Veerkar
Author-email: bzubs011@gmail.com
License: MIT
Classifier: Programming Language :: Python :: 3
Classifier: License :: OSI Approved :: MIT License
Classifier: Operating System :: OS Independent
Requires-Python: >=3.7
Requires-Dist: numpy
Requires-Dist: matplotlib
Dynamic: author
Dynamic: author-email
Dynamic: classifier
Dynamic: description
Dynamic: description-content-type
Dynamic: home-page
Dynamic: license
Dynamic: requires-dist
Dynamic: requires-python
Dynamic: summary
